globalfirepower.py
globalfirepower_scraper-0.2.1.dist-info/METADATA
globalfirepower_scraper-0.2.1.dist-info/WHEEL
globalfirepower_scraper-0.2.1.dist-info/top_level.txt
globalfirepower_scraper-0.2.1.dist-info/RECORD
