Metadata-Version: 2.1
Name: globalfirepower-scraper
Version: 0.2.1
Summary: Global FirePower Scraper
Home-page: https://github.com/mickaelandrieu/global-firepower-scraper
Author: Mickaël Andrieu
Author-email: mickael.andrieu@solvolabs.com
License: UNKNOWN
Platform: UNKNOWN
Classifier: Programming Language :: Python :: 3
Classifier: License :: OSI Approved :: MIT License
Classifier: Operating System :: OS Independent
Requires-Python: >=3.9
Requires-Dist: aiohttp (==3.8.1)
Requires-Dist: asyncio (==3.4.3)
Requires-Dist: bs4 (==0.0.1)
Requires-Dist: pandas (>=1.3.0)
Requires-Dist: cloudscraper (==1.2.60)
Requires-Dist: aiocfscrape (==1.0.0)
Requires-Dist: lxml (==4.8.0)
